Workbook

Sheet Date_sheet
A1: Date | B1: Year | C1: Month_Number | D1: Month_Name | E1: Quarter | F1: Weekday | G1: Is_Weekend
A2: 45809 | B2: =YEAR(A2) -> 2025 | C2: =MONTH(A2) -> 6 | D2: =TEXT(A2,"mmmm") -> June | E2: ="Q"&ROUNDUP(MONTH(A2)/3,0) -> Q2 | F2: =TEXT(A2,"dddd") -> Sunday | G2: =IF(OR(WEEKDAY(A2)=1,WEEKDAY(A2)=7),"Yes","No") -> Yes
A3: 45810 | B3: =YEAR(A3) -> 2025 | C3: =MONTH(A3) -> 6 | D3: =TEXT(A3,"mmmm") -> June | E3: ="Q"&ROUNDUP(MONTH(A3)/3,0) -> Q2 | F3: =TEXT(A3,"dddd") -> Monday | G3: =IF(OR(WEEKDAY(A3)=1,WEEKDAY(A3)=7),"Yes","No") -> No
A4: 45811 | B4: =YEAR(A4) -> 2025 | C4: =MONTH(A4) -> 6 | D4: =TEXT(A4,"mmmm") -> June | E4: ="Q"&ROUNDUP(MONTH(A4)/3,0) -> Q2 | F4: =TEXT(A4,"dddd") -> Tuesday | G4: =IF(OR(WEEKDAY(A4)=1,WEEKDAY(A4)=7),"Yes","No") -> No
A5: 45812 | B5: =YEAR(A5) -> 2025 | C5: =MONTH(A5) -> 6 | D5: =TEXT(A5,"mmmm") -> June | E5: ="Q"&ROUNDUP(MONTH(A5)/3,0) -> Q2 | F5: =TEXT(A5,"dddd") -> Wednesday | G5: =IF(OR(WEEKDAY(A5)=1,WEEKDAY(A5)=7),"Yes","No") -> No
A6: 45813 | B6: =YEAR(A6) -> 2025 | C6: =MONTH(A6) -> 6 | D6: =TEXT(A6,"mmmm") -> June | E6: ="Q"&ROUNDUP(MONTH(A6)/3,0) -> Q2 | F6: =TEXT(A6,"dddd") -> Thursday | G6: =IF(OR(WEEKDAY(A6)=1,WEEKDAY(A6)=7),"Yes","No") -> No
A7: 45814 | B7: =YEAR(A7) -> 2025 | C7: =MONTH(A7) -> 6 | D7: =TEXT(A7,"mmmm") -> June | E7: ="Q"&ROUNDUP(MONTH(A7)/3,0) -> Q2 | F7: =TEXT(A7,"dddd") -> Friday | G7: =IF(OR(WEEKDAY(A7)=1,WEEKDAY(A7)=7),"Yes","No") -> No
A8: 45815 | B8: =YEAR(A8) -> 2025 | C8: =MONTH(A8) -> 6 | D8: =TEXT(A8,"mmmm") -> June | E8: ="Q"&ROUNDUP(MONTH(A8)/3,0) -> Q2 | F8: =TEXT(A8,"dddd") -> Saturday | G8: =IF(OR(WEEKDAY(A8)=1,WEEKDAY(A8)=7),"Yes","No") -> Yes
A9: 45816 | B9: =YEAR(A9) -> 2025 | C9: =MONTH(A9) -> 6 | D9: =TEXT(A9,"mmmm") -> June | E9: ="Q"&ROUNDUP(MONTH(A9)/3,0) -> Q2 | F9: =TEXT(A9,"dddd") -> Sunday | G9: =IF(OR(WEEKDAY(A9)=1,WEEKDAY(A9)=7),"Yes","No") -> Yes
A10: 45817 | B10: =YEAR(A10) -> 2025 | C10: =MONTH(A10) -> 6 | D10: =TEXT(A10,"mmmm") -> June | E10: ="Q"&ROUNDUP(MONTH(A10)/3,0) -> Q2 | F10: =TEXT(A10,"dddd") -> Monday | G10: =IF(OR(WEEKDAY(A10)=1,WEEKDAY(A10)=7),"Yes","No") -> No
A11: 45818 | B11: =YEAR(A11) -> 2025 | C11: =MONTH(A11) -> 6 | D11: =TEXT(A11,"mmmm") -> June | E11: ="Q"&ROUNDUP(MONTH(A11)/3,0) -> Q2 | F11: =TEXT(A11,"dddd") -> Tuesday | G11: =IF(OR(WEEKDAY(A11)=1,WEEKDAY(A11)=7),"Yes","No") -> No
A12: 45819 | B12: =YEAR(A12) -> 2025 | C12: =MONTH(A12) -> 6 | D12: =TEXT(A12,"mmmm") -> June | E12: ="Q"&ROUNDUP(MONTH(A12)/3,0) -> Q2 | F12: =TEXT(A12,"dddd") -> Wednesday | G12: =IF(OR(WEEKDAY(A12)=1,WEEKDAY(A12)=7),"Yes","No") -> No
A13: 45820 | B13: =YEAR(A13) -> 2025 | C13: =MONTH(A13) -> 6 | D13: =TEXT(A13,"mmmm") -> June | E13: ="Q"&ROUNDUP(MONTH(A13)/3,0) -> Q2 | F13: =TEXT(A13,"dddd") -> Thursday | G13: =IF(OR(WEEKDAY(A13)=1,WEEKDAY(A13)=7),"Yes","No") -> No
... A215: 46022 | B215: =YEAR(A215) -> 2025 | C215: =MONTH(A215) -> 12 | D215: =TEXT(A215,"mmmm") -> December | E215: ="Q"&ROUNDUP(MONTH(A215)/3,0) -> Q4 | F215: =TEXT(A215,"dddd") -> Wednesday | G215: =IF(OR(WEEKDAY(A215)=1,WEEKDAY(A215)=7),"Yes","No") -> No

Sheet Customer_sheet
A1: Customer_ID | B1: Gender (Male / Female /Other) | C1: Age_Group | D1: Repeat
A2: CUSID0001 | B2: Female | C2: 15-25 | D2: =IF(COUNTIF(Order_sheet!B:B, A2)>1,"Yes","No") -> No
A3: CUSID0002 | B3: Female | C3: 25-35 | D3: =IF(COUNTIF(Order_sheet!B:B, A3)>1,"Yes","No") -> No
A4: CUSID0003 | B4: Female | C4: 15-25 | D4: =IF(COUNTIF(Order_sheet!B:B, A4)>1,"Yes","No") -> Yes
A5: CUSID0004 | B5: Female | C5: 15-25 | D5: =IF(COUNTIF(Order_sheet!B:B, A5)>1,"Yes","No") -> No
A6: CUSID0005 | B6: Female | C6: 15-25 | D6: =IF(COUNTIF(Order_sheet!B:B, A6)>1,"Yes","No") -> No
A7: CUSID0006 | B7: Female | C7: 15-25 | D7: =IF(COUNTIF(Order_sheet!B:B, A7)>1,"Yes","No") -> No
A8: CUSID0007 | B8: Female | C8: 25-35 | D8: =IF(COUNTIF(Order_sheet!B:B, A8)>1,"Yes","No") -> No
A9: CUSID0008 | B9: Male | C9: 15-25 | D9: =IF(COUNTIF(Order_sheet!B:B, A9)>1,"Yes","No") -> No
A10: CUSID0009 | B10: Female | C10: 25-35 | D10: =IF(COUNTIF(Order_sheet!B:B, A10)>1,"Yes","No") -> No
A11: CUSID0010 | B11: Male | C11: 15-25 | D11: =IF(COUNTIF(Order_sheet!B:B, A11)>1,"Yes","No") -> No
A12: CUSID0011 | B12: Female | C12: 15-25 | D12: =IF(COUNTIF(Order_sheet!B:B, A12)>1,"Yes","No") -> No
A13: CUSID0012 | B13: Male | C13: 15-25 | D13: =IF(COUNTIF(Order_sheet!B:B, A13)>1,"Yes","No") -> No
... A141: CUSID0140 | B141: Male | C141: 15-25 | D141: =IF(COUNTIF(Order_sheet!B:B, A141)>1,"Yes","No") -> No
A142: CUSID0141 | B142: Female | C142: 25-35 | D142: =IF(COUNTIF(Order_sheet!B:B, A143)>1,"Yes","No") -> No
A143: CUSID0142 | B143: Female | C143: 25-35 | D143: =IF(COUNTIF(Order_sheet!B:B, A144)>1,"Yes","No") -> No
A144: CUSID0143 | B144: Female | C144: 15-25 | D144: =IF(COUNTIF(Order_sheet!B:B, A145)>1,"Yes","No") -> No
A145: CUSID0144 | B145: Female | C145: 25-35 | D145: =IF(COUNTIF(Order_sheet!B:B, A146)>1,"Yes","No") -> No
A146: CUSID0145 | B146: Male | C146: 15-25 | D146: =IF(COUNTIF(Order_sheet!B:B, A147)>1,"Yes","No") -> No

Sheet Order_sheet
A1: Order_ID | B1: Customer_ID | C1: Order_Date | D1: Delivery_Date | E1: City/Destination | F1: Payment_Mode (UPI / Cash / Bank Transfer
A2: ORDID0001 | B2: CUSID0001 | C2: 45797 | D2: 45813 | E2: Uttar Pradesh | F2: UPI
A3: ORDID0002 | B3: CUSID0002 | C3: 45797 | D3: 45810 | E3: Karimganj, Assam | F3: Cash
A4: ORDID0003 | B4: CUSID0003 | C4: 45802 | D4: 45811 | E4: Silchar, Assam | F4: UPI
A5: ORDID0004 | B5: CUSID0004 | C5: 45805 | D5: 45812 | E5: Guwahati, Assam | F5: UPI
A6: ORDID0005 | B6: CUSID0005 | C6: 45812 | D6: 45817 | E6: Karimganj, Assam | F6: Cash
A7: ORDID0006 | B7: CUSID0006 | C7: 45812 | D7: 45819 | E7: Silchar, Assam | F7: Cash
A8: ORDID0007 | B8: CUSID0007 | C8: 45813 | D8: 45814 | E8: Karimganj, Assam | F8: Cash
A9: ORDID0008 | B9: CUSID0008 | C9: 45813 | D9: 45818 | E9: Karimganj, Assam | F9: Cash
A10: ORDID0009 | B10: CUSID0009 | C10: 45813 | D10: 45826 | E10: Bengaluru, Karnataka | F10: UPI
A11: ORDID0010 | B11: CUSID0003 | C11: 45815 | D11: 45831 | E11: Nagaon, Assam | F11: UPI
A12: ORDID0011 | B12: CUSID0010 | C12: 45818 | D12: 45819 | E12: Karimganj, Assam | F12: UPI
A13: ORDID0012 | B13: CUSID0011 | C13: 45818 | D13: 45823 | E13: Silchar, Assam | F13: UPI
... A162: ORDID0161 | B162: CUSID0145 | C162: 46011 | D162: 46015 | E162: Karimganj, Assam | F162: Cash

Sheet Sales_sheet
A1: Order_ID | B1: Sales_ID | C1: Product_Name | D1: Category | E1: Quantity Number of units sold | F1: Unit_Price | G1: Unit_Cost | H1: Total value | I1: Total_Cost | J1: Total_Profit
A2: ORDID0001 | B2: SID0001 | C2: Canvas painting(small) | D2: Decoration | E2: 1 | F2: 100 | G2: 50 | H2: =E2*F2 -> 100 | I2: =E2*G2 -> 50 | J2: =H2-I2 -> 50
A3: ORDID0002 | B3: SID0002 | C3: Customized wedding frame | D3: Frames | E3: 1 | F3: 1500 | G3: 1000 | H3: =E3*F3 -> 1500 | I3: =E3*G3 -> 1000 | J3: =H3-I3 -> 500
A4: ORDID0003 | B4: SID0003 | C4: Heart glass Jar candle | D4: Candle | E4: 1 | F4: 500 | G4: 350 | H4: =E4*F4 -> 500 | I4: =E4*G4 -> 350 | J4: =H4-I4 -> 150
A5: ORDID0003 | B5: SID0004 | C5: Ferro rocher chocolate bouquet | D5: Bouquet | E5: 1 | F5: 250 | G5: 200 | H5: =E5*F5 -> 250 | I5: =E5*G5 -> 200 | J5: =H5-I5 -> 50
A6: ORDID0004 | B6: SID0005 | C6: Vintage Brass Photo Frame(Medium) | D6: Frames | E6: 1 | F6: 800 | G6: 700 | H6: =E6*F6 -> 800 | I6: =E6*G6 -> 700 | J6: =H6-I6 -> 100
A7: ORDID0005 | B7: SID0006 | C7: Strawbery glass jar candle | D7: Candle | E7: 1 | F7: 400 | G7: 300 | H7: =E7*F7 -> 400 | I7: =E7*G7 -> 300 | J7: =H7-I7 -> 100
A8: ORDID0006 | B8: SID0007 | C8: Lavender latte candle | D8: Candle | E8: 1 | F8: 250 | G8: 180 | H8: =E8*F8 -> 250 | I8: =E8*G8 -> 180 | J8: =H8-I8 -> 70
A9: ORDID0007 | B9: SID0008 | C9: Customized resin phone back cover | D9: Accessories | E9: 1 | F9: 100 | G9: 50 | H9: =E9*F9 -> 100 | I9: =E9*G9 -> 50 | J9: =H9-I9 -> 50
A10: ORDID0008 | B10: SID0009 | C10: secret message candle | D10: Candle | E10: 1 | F10: 300 | G10: 220 | H10: =E10*F10 -> 300 | I10: =E10*G10 -> 220 | J10: =H10-I10 -> 80
A11: ORDID0009 | B11: SID0010 | C11: Customized resin photo frame | D11: Frames | E11: 1 | F11: 600 | G11: 450 | H11: =E11*F11 -> 600 | I11: =E11*G11 -> 450 | J11: =H11-I11 -> 150
A12: ORDID0010 | B12: SID0011 | C12: Birthday hamper | D12: Hamper | E12: 1 | F12: 400 | G12: 320 | H12: =E12*F12 -> 400 | I12: =E12*G12 -> 320 | J12: =H12-I12 -> 80
A13: ORDID0011 | B13: SID0012 | C13: Customized phone back cover | D13: Accessories | E13: 1 | F13: 100 | G13: 50 | H13: =E13*F13 -> 100 | I13: =E13*G13 -> 50 | J13: =H13-I13 -> 50
... A179: ORDID0161 | B179: SID0178 | C179: Rose bouquet | D179: Decoration | E179: 1 | F179: 150 | G179: 80 | H179: =E179*F179 -> 150 | I179: =E179*G179 -> 80 | J179: =H179-I179 -> 70

Sheet Inventory_sheet
A1: Product_Name | B1: Category | C1: Current_Stock | D1: Reorder_Level | E1: Unit | F1: Inventory_Status
A2: Soy Wax | B2: candles | C2: 5 | D2: 3 | E2: Kgs | F2: =IF(C2<=D2,"Low Stock","Sufficient") -> Sufficient
A3: Gel Wax | B3: candles | C3: 5 | D3: 3 | E3: Kgs | F3: =IF(C3<=D3,"Low Stock","Sufficient") -> Sufficient
A4: Wick (Cotton) | B4: candles | C4: 1 | D4: 2 | E4: Bundles | F4: =IF(C4<=D4,"Low Stock","Sufficient") -> Low Stock
A5: Candle Fragrance Oils | B5: candles | C5: 2 | D5: 3 | E5: Bottles | F5: =IF(C5<=D5,"Low Stock","Sufficient") -> Low Stock
A6: Candle Colour Dye | B6: candles | C6: 5 | D6: 2 | E6: Boxes | F6: =IF(C6<=D6,"Low Stock","Sufficient") -> Sufficient
A7: Glass Jars (Small/Medium/Large) | B7: candles | C7: 50 | D7: 20 | E7: Pieces | F7: =IF(C7<=D7,"Low Stock","Sufficient") -> Sufficient
A8: Urli Candle Moulds | B8: candles | C8: 20 | D8: 25 | E8: Pieces | F8: =IF(C8<=D8,"Low Stock","Sufficient") -> Low Stock
A9: Flower Candle Moulds | B9: candles | C9: 30 | D9: 20 | E9: Pieces | F9: =IF(C9<=D9,"Low Stock","Sufficient") -> Sufficient
A10: Diya Candle Moulds | B10: candles | C10: 18 | D10: 25 | E10: Pieces | F10: =IF(C10<=D10,"Low Stock","Sufficient") -> Low Stock
A11: Decorative Candle Toppers | B11: candles | C11: 30 | D11: 25 | E11: Pieces | F11: =IF(C11<=D11,"Low Stock","Sufficient") -> Sufficient
A12: Epoxy Resin | B12: Decoration | C12: 3 | D12: 5 | E12: Kgs | F12: =IF(C12<=D12,"Low Stock","Sufficient") -> Low Stock
A13: Resin Hardener | B13: Decoration | C13: 4 | D13: 2 | E13: Bottles | F13: =IF(C13<=D13,"Low Stock","Sufficient") -> Sufficient
... A49: Photoframe stand | B49: Frames | C49: 20 | D49: 10 | E49: Pieces | F49: =IF(C49<=D49,"Low Stock","Sufficient") -> Sufficient
